cmdvars/__init__.py
cmdvars/_version.py
cmdvars-0.1.3.dist-info/DESCRIPTION.rst
cmdvars-0.1.3.dist-info/METADATA
cmdvars-0.1.3.dist-info/RECORD
cmdvars-0.1.3.dist-info/WHEEL
cmdvars-0.1.3.dist-info/metadata.json
cmdvars-0.1.3.dist-info/top_level.txt
