Metadata-Version: 2.0
Name: cmdvars
Version: 0.1.3
Summary: Read environment variables defined in a shell script into Python.
Home-page: http://github.com/xoviat/cmdvars
Author: Mars Galactic
Author-email: xoviat@users.noreply.github.com
License: Apache2
Platform: UNKNOWN
Classifier: Intended Audience :: Developers
Classifier: Natural Language :: English
Classifier: License :: OSI Approved :: Apache Software License
Classifier: Operating System :: MacOS :: MacOS X
Classifier: Operating System :: POSIX
Classifier: Programming Language :: Python
Classifier: Programming Language :: Python :: 3
Classifier: Topic :: Software Development :: Libraries :: Python Modules
